examples/__init__.py
examples/accordeon_wizard/__init__.py
examples/accordeon_wizard/accordeon_wizard/__init__.py
examples/accordeon_wizard/accordeon_wizard/settings.py
examples/accordeon_wizard/accordeon_wizard/urls.py
examples/accordeon_wizard/testapp/__init__.py
examples/accordeon_wizard/testapp/forms.py
examples/accordeon_wizard/testapp/urls.py
examples/accordeon_wizard/testapp/views.py
formtools_addons/__init__.py
formtools_addons/enums.py
formtools_addons/middleware.py
formtools_addons/models.py
formtools_addons/static/formtools_addons/css/formtools_addons.css
formtools_addons/static/formtools_addons/js/wizardapi.js
formtools_addons/static/formtools_addons/templates/directives/wizardapi/wizard.html
formtools_addons/templates/formtools_addons/wizard/wizard_form.html
formtools_addons/wizard/__init__.py
formtools_addons/wizard/views/__init__.py
formtools_addons/wizard/views/multipleformwizard.py
formtools_addons/wizard/views/wizardapi.py
tests/__init__.py
tests/forms.py
tests/settings.py
tests/tests.py
tests/urls.py
tests/wizard/__init__.py
tests/wizard/storage.py
tests/wizard/test_cookiestorage.py
tests/wizard/test_forms.py
tests/wizard/test_loadstorage.py
tests/wizard/test_sessionstorage.py
tests/wizard/namedwizardtests/__init__.py
tests/wizard/namedwizardtests/forms.py
tests/wizard/namedwizardtests/tests.py
tests/wizard/namedwizardtests/urls.py
tests/wizard/wizardapitests/__init__.py
tests/wizard/wizardapitests/forms.py
tests/wizard/wizardapitests/tests.py
tests/wizard/wizardapitests/urls.py
tests/wizard/wizardtests/__init__.py
tests/wizard/wizardtests/forms.py
tests/wizard/wizardtests/models.py
tests/wizard/wizardtests/tests.py
tests/wizard/wizardtests/urls.py
django2_formtools_addons-0.2.2.dist-info/AUTHORS.rst
django2_formtools_addons-0.2.2.dist-info/LICENSE
django2_formtools_addons-0.2.2.dist-info/METADATA
django2_formtools_addons-0.2.2.dist-info/WHEEL
django2_formtools_addons-0.2.2.dist-info/top_level.txt
django2_formtools_addons-0.2.2.dist-info/RECORD
