Metadata-Version: 2.1
Name: django2-formtools-addons
Version: 0.2.2
Summary: 'Addons for Django 2 Formtools'
Home-page: https://github.com/hpe95/django-formtools-addons
Author: VikingCo
Author-email: technology@vikingco.com
License: BSD
Keywords: django2-formtools-addons
Platform: UNKNOWN
Classifier: Development Status :: 3 - Alpha
Classifier: Framework :: Django
Classifier: Framework :: Django :: 2.2
Classifier: Intended Audience :: Developers
Classifier: License :: OSI Approved :: BSD License
Classifier: Natural Language :: English
Classifier: Programming Language :: Python :: 3
Classifier: Programming Language :: Python :: 3.3
Classifier: Programming Language :: Python :: 3.4
Classifier: Programming Language :: Python :: 3.5
License-File: LICENSE
License-File: AUTHORS.rst
Requires-Dist: django (>=2.1)
Requires-Dist: six (>=1.9)
